Exceptions/HologramError.py
Exceptions/__init__.py
Hologram/Cloud.py
Hologram/CustomCloud.py
Hologram/HologramCloud.py
Hologram/__init__.py
Hologram/Api/Api.py
Hologram/Api/__init__.py
Hologram/Authentication/Authentication.py
Hologram/Authentication/CSRPSKAuthentication.py
Hologram/Authentication/HologramAuthentication.py
Hologram/Authentication/__init__.py
Hologram/Authentication/AES/AESCipher.py
Hologram/Event/Event.py
Hologram/Event/__init__.py
Hologram/Network/BLE.py
Hologram/Network/Cellular.py
Hologram/Network/Ethernet.py
Hologram/Network/Network.py
Hologram/Network/NetworkManager.py
Hologram/Network/Route.py
Hologram/Network/Wifi.py
Hologram/Network/__init__.py
Hologram/Network/Modem/BG96.py
Hologram/Network/Modem/DriverLoader.py
Hologram/Network/Modem/E303.py
Hologram/Network/Modem/E372.py
Hologram/Network/Modem/EC21.py
Hologram/Network/Modem/EC25.py
Hologram/Network/Modem/IModem.py
Hologram/Network/Modem/MS2131.py
Hologram/Network/Modem/MockModem.py
Hologram/Network/Modem/Modem.py
Hologram/Network/Modem/Nova.py
Hologram/Network/Modem/NovaM.py
Hologram/Network/Modem/Nova_U201.py
Hologram/Network/Modem/Quectel.py
Hologram/Network/Modem/__init__.py
Hologram/Network/Modem/ModemMode/IPPP.py
Hologram/Network/Modem/ModemMode/MockPPP.py
Hologram/Network/Modem/ModemMode/ModemMode.py
Hologram/Network/Modem/ModemMode/PPP.py
Hologram/Network/Modem/ModemMode/__init__.py
Hologram/Network/Modem/ModemMode/pppd.py
Hologram/Network/Modem/chatscripts/__init__.py
Hologram/Network/Modem/chatscripts/default-script
UtilClasses/UtilClasses.py
UtilClasses/__init__.py
hologram_python-0.10.3.data/scripts/hologram
scripts/__init__.py
scripts/hologram
scripts/hologram_activate.py
scripts/hologram_heartbeat.py
scripts/hologram_modem.py
scripts/hologram_network.py
scripts/hologram_receive.py
scripts/hologram_send.py
scripts/hologram_spacebridge.py
scripts/hologram_util.py
hologram_python-0.10.3.dist-info/AUTHORS.md
hologram_python-0.10.3.dist-info/LICENSE
hologram_python-0.10.3.dist-info/METADATA
hologram_python-0.10.3.dist-info/WHEEL
hologram_python-0.10.3.dist-info/top_level.txt
hologram_python-0.10.3.dist-info/RECORD
