Metadata-Version: 2.1
Name: hologram-python
Version: 0.10.3
Summary: Library for accessing Hologram Cloud at https://hologram.io
Home-page: https://github.com/hologram-io/hologram-python/
Author: Hologram
Author-email: support@hologram.io
License: MIT
Platform: Posix; MacOS X; Windows
Classifier: Development Status :: 5 - Production/Stable
Classifier: Intended Audience :: Developers
Classifier: License :: OSI Approved :: MIT License
Classifier: Operating System :: OS Independent
Classifier: Topic :: Internet
Classifier: Topic :: Security :: Cryptography
Classifier: Programming Language :: Python
Classifier: Programming Language :: Python :: 3.9
License-File: LICENSE
License-File: AUTHORS.md
Requires-Dist: pyroute2==0.5.*
Requires-Dist: pyserial~=3.5
Requires-Dist: python-pppd==1.0.4
Requires-Dist: python-sdk-auth==0.4.0
Requires-Dist: pyudev~=0.22.0
Requires-Dist: pyusb~=1.2.1
Requires-Dist: psutil~=5.8.0
Requires-Dist: requests>=2.25.1
